MANIFEST.in
readme.md
setup.py
direct_render/__init__.py
direct_render/admin.py
direct_render/models.py
direct_render/tests.py
direct_render/urls.py
direct_render/views.py
django_direct_render.egg-info/PKG-INFO
django_direct_render.egg-info/SOURCES.txt
django_direct_render.egg-info/dependency_links.txt
django_direct_render.egg-info/top_level.txt