Metadata-Version: 1.1
Name: django-direct-render
Version: 0.1.2
Summary: A simple Django app that will render template directly for you
Home-page: https://github.com/timtan/django_direct_render
Author: Tim Hsu
Author-email: tim.yellow@gmail.com
License: BSD License
Platform: UNKNOWN
Classifier: Environment :: Web Environment
Classifier: Framework :: Django
Classifier: Intended Audience :: Developers
Classifier: License :: OSI Approved :: BSD License
Classifier: Operating System :: OS Independent
Classifier: Programming Language :: Python
